janis/__init__.py
janis/__meta__.py
janis/data_types/__init__.py
janis/tools/__init__.py
janisdk/__init__.py
janisdk/main.py
janisdk/container/__init__.py
janisdk/container/parse_help.py
janisdk/container/test_cltbuilder.py
janisdk/fromcwl/__init__.py
janisdk/fromwdl/__init__.py
janisdk/runtest/__init__.py
janisdk/runtest/runner.py
janis_pipelines-0.13.1.dist-info/LICENSE
janis_pipelines-0.13.1.dist-info/METADATA
janis_pipelines-0.13.1.dist-info/WHEEL
janis_pipelines-0.13.1.dist-info/entry_points.txt
janis_pipelines-0.13.1.dist-info/top_level.txt
janis_pipelines-0.13.1.dist-info/RECORD
