Metadata-Version: 2.1
Name: janis-pipelines
Version: 0.13.1
Summary: Contains classes and helpers to build a workflow, and provide options to convert to CWL / WDL
Home-page: https://github.com/PMCC-BioinformaticsCore/janis
Author: Michael Franklin, Richard Lupat
Author-email: michael.franklin@petermac.org
License: GNU
Keywords: pipelines,bioinformatics
Platform: UNKNOWN
Classifier: Development Status :: 2 - Pre-Alpha
Classifier: Intended Audience :: Developers
Classifier: Intended Audience :: Science/Research
Classifier: Topic :: Scientific/Engineering
Classifier: Topic :: Scientific/Engineering :: Bio-Informatics
License-File: LICENSE
Requires-Dist: janis-pipelines.core ==v0.13.1
Requires-Dist: janis-pipelines.runner ==v0.13.0
Requires-Dist: janis-pipelines.unix ==v0.12.0
Requires-Dist: janis-pipelines.bioinformatics ==v0.12.2
Requires-Dist: janis-pipelines.pipelines ==v0.13.0
Requires-Dist: janis-pipelines.templates ==v0.12.0
Provides-Extra: bioinformatics
Requires-Dist: janis-pipelines.bioinformatics ==v0.12.2 ; extra == 'bioinformatics'
Requires-Dist: janis-pipelines.pipelines ==v0.13.0 ; extra == 'bioinformatics'
Provides-Extra: ci
Requires-Dist: keyring ==21.4.0 ; extra == 'ci'
Requires-Dist: setuptools ; extra == 'ci'
Requires-Dist: wheel ; extra == 'ci'
Requires-Dist: twine ; extra == 'ci'
Provides-Extra: doc
Requires-Dist: docutils ; extra == 'doc'
Requires-Dist: sphinx ; extra == 'doc'
Requires-Dist: sphinx-rtd-theme ; extra == 'doc'
Requires-Dist: recommonmark ; extra == 'doc'
